ml_spikeforest/__init__.py
ml_spikeforest/kbuckethdf5file.py
ml_spikeforest/ml_spikeforest.py
ml_spikeforest/ml_spikeforest.py.mp
ml_spikeforest/timeserieshdf5reader.py
ml_spikeforest/timeseriesmdareader.py
ml_spikeforest-0.1.7.dist-info/METADATA
ml_spikeforest-0.1.7.dist-info/RECORD
ml_spikeforest-0.1.7.dist-info/WHEEL
ml_spikeforest-0.1.7.dist-info/top_level.txt
