Metadata-Version: 2.1
Name: ml-spikeforest
Version: 0.1.7
Summary: MountainLab package with spike sorting utilities
Home-page: https://github.com/magland/ml_spikeforest
Author: Jeremy Magland
Author-email: 
License: UNKNOWN
Platform: UNKNOWN
Classifier: Programming Language :: Python :: 3
Classifier: License :: OSI Approved :: Apache Software License
Classifier: Operating System :: OS Independent
Requires-Dist: numpy
Requires-Dist: mountainlab-pytools
Requires-Dist: mlprocessors
Requires-Dist: h5py
